safemx/__init__.py
safemx/checkers.py
safemx/explanations.py
safemx/main.py
safemx/parsers.py
safemx-0.1.7.dist-info/LICENSE
safemx-0.1.7.dist-info/METADATA
safemx-0.1.7.dist-info/WHEEL
safemx-0.1.7.dist-info/entry_points.txt
safemx-0.1.7.dist-info/top_level.txt
safemx-0.1.7.dist-info/RECORD
