Metadata-Version: 2.1
Name: safemx
Version: 0.1.7
Summary: A tool to check domain's SPF, DMARC, and DKIM records.
Home-page: https://github.com/MarkoGordic/safemx
Author: Marko Gordic
Author-email: marko@gordic.rs
Classifier: Programming Language :: Python :: 3
Classifier: License :: OSI Approved :: MIT License
Classifier: Operating System :: OS Independent
Requires-Python: >=3.6
License-File: LICENSE
Requires-Dist: argparse
Requires-Dist: colorama
Requires-Dist: dnspython
